requests_jwt.py
requests_jwt-0.6.0.dist-info/DESCRIPTION.rst
requests_jwt-0.6.0.dist-info/METADATA
requests_jwt-0.6.0.dist-info/RECORD
requests_jwt-0.6.0.dist-info/WHEEL
requests_jwt-0.6.0.dist-info/metadata.json
requests_jwt-0.6.0.dist-info/top_level.txt
