Metadata-Version: 2.0
Name: requests-jwt
Version: 0.6.0
Summary: This package allows for HTTP JSON Web Token (JWT) authentication using the requests library.
Home-page: https://github.com/tgs/requests-jwt
Author: Thomas Grenfell Smith
Author-email: thomathom@gmail.com
License: ISC
Platform: UNKNOWN
Classifier: Development Status :: 4 - Beta
Classifier: Intended Audience :: Developers
Classifier: Programming Language :: Python
Classifier: Programming Language :: Python :: 2.7
Classifier: Programming Language :: Python :: 3.6
Classifier: Programming Language :: Python :: 3.7
Classifier: Programming Language :: Python :: 3.8
Classifier: Programming Language :: Python :: 3.9
Classifier: License :: OSI Approved :: ISC License (ISCL)
Provides: requests_jwt
Requires-Dist: PyJWT
Requires-Dist: requests
